graal/_version.py
graal/backends/core/__init__.py
graal/backends/core/analyzers/__init__.py
graal/backends/core/analyzers/analyzer.py
graal/backends/core/analyzers/bandit.py
graal/backends/core/analyzers/cloc.py
graal/backends/core/analyzers/flake8.py
graal/backends/core/analyzers/jadolint.py
graal/backends/core/analyzers/linguist.py
graal/backends/core/analyzers/lizard.py
graal/backends/core/analyzers/nomos.py
graal/backends/core/analyzers/pylint.py
graal/backends/core/analyzers/reverse.py
graal/backends/core/analyzers/scancode.py
graal/backends/core/analyzers/scc.py
graal/backends/core/cocom.py
graal/backends/core/codep.py
graal/backends/core/colang.py
graal/backends/core/colic.py
graal/backends/core/coqua.py
graal/backends/core/covuln.py
graal/bin/graal.py
graal/graal.py
graal-1.2.6.dist-info/METADATA
graal-1.2.6.dist-info/WHEEL
graal-1.2.6.dist-info/entry_points.txt
graal-1.2.6.dist-info/licenses/AUTHORS
graal-1.2.6.dist-info/licenses/LICENSE
graal-1.2.6.dist-info/RECORD
