Metadata-Version: 2.4
Name: graal
Version: 1.2.6
Summary: A generic source code analyzer
License: GPL-3.0+
License-File: AUTHORS
License-File: LICENSE
Keywords: development,grimoirelab
Author: GrimoireLab Developers
Requires-Python: >=3.10,<4.0
Classifier: Development Status :: 5 - Production/Stable
Classifier: Intended Audience :: Developers
Classifier: Intended Audience :: Science/Research
Classifier: License :: OSI Approved :: GNU General Public License v3 or later (GPLv3+)
Classifier: Programming Language :: Python :: 3
Classifier: Programming Language :: Python :: 3.10
Classifier: Programming Language :: Python :: 3.11
Classifier: Programming Language :: Python :: 3.12
Classifier: Programming Language :: Python :: 3.13
Classifier: Programming Language :: Python :: 3.14
Classifier: Topic :: Software Development
Requires-Dist: bandit (>=1.4.0)
Requires-Dist: cloc (>=0.2.5,<0.3.0)
Requires-Dist: execnet (>=2.1.1,<3.0.0)
Requires-Dist: flake8 (>=7.1.1,<8.0.0)
Requires-Dist: grimoirelab-toolkit (>=0.3)
Requires-Dist: lizard (>=1.16.6,<2.0.0)
Requires-Dist: markdown-it-py (>=2.0.0,<3.0.0)
Requires-Dist: networkx (>=2.1)
Requires-Dist: perceval (>=0.19)
Requires-Dist: pydot (>=1.2.4)
Requires-Dist: pylint (>=1.8.4)
Project-URL: Bug Tracker, https://github.com/chaoss/grimoirelab-graal/issues
Project-URL: Homepage, https://chaoss.github.io/grimoirelab/
Project-URL: Repository, https://github.com/chaoss/grimoirelab-graal
